<?xml version="1.0" encoding="UTF-8"?><database>
    <element db_object_id="45367d3647594210bea54db3416d4362" label="My New Application" max_length="40" name="x_13792_my_new_app_my_new_application" type="collection">
        <element default="javascript:current.getTableName();" label="Class" max_length="80" name="sys_class_name" type="sys_class_name"/>
        <element attributes="edge_encryption_enabled=true" default="javascript:global.getNextObjNumberPadded();" label="Number" max_length="40" name="number" type="string"/>
        <element attributes="edge_encryption_enabled=true" choice="1" label="Sub Group" max_length="40" name="sub_group" type="choice">
            <choice/>
        </element>
        <index name="index">
            <element name="sys_class_name"/>
        </index>
    </element>
</database>
